ImgurDownloader-1.0.dist-info/DESCRIPTION.rst
ImgurDownloader-1.0.dist-info/METADATA
ImgurDownloader-1.0.dist-info/RECORD
ImgurDownloader-1.0.dist-info/WHEEL
ImgurDownloader-1.0.dist-info/entry_points.txt
ImgurDownloader-1.0.dist-info/metadata.json
ImgurDownloader-1.0.dist-info/top_level.txt
imgurdownloader/__init__.py
